MANIFEST.in
setup.py
freecad/__init__.py
freecad/modules/__init__.py
freecad/modules/fc_gear/__init__.py
freecad/modules/fc_gear/init_gui.py
freecad/modules/fc_gear/gearfunc/_Classes.py
freecad/modules/fc_gear/gearfunc/__init__.py
freecad/modules/fc_gear/gearfunc/_bevel_tooth.py
freecad/modules/fc_gear/gearfunc/_cycloide_tooth.py
freecad/modules/fc_gear/gearfunc/_functions.py
freecad/modules/fc_gear/gearfunc/_involute_tooth.py
freecad/modules/fc_gear/resources/icons/bevelgear.svg
freecad/modules/fc_gear/resources/icons/cycloidegear.svg
freecad/modules/fc_gear/resources/icons/gearworkbench.svg
freecad/modules/fc_gear/resources/icons/involutegear.svg
freecad/modules/fc_gear/resources/icons/involuterack.svg
freecad_fc_gear.egg-info/PKG-INFO
freecad_fc_gear.egg-info/SOURCES.txt
freecad_fc_gear.egg-info/dependency_links.txt
freecad_fc_gear.egg-info/requires.txt
freecad_fc_gear.egg-info/top_level.txt