Metadata-Version: 1.0
Name: freecad-fc-gear
Version: 0.0.1
Summary: Gear-workbench for freecad
Home-page: https://github.com/looooo/FCGear
Author: looooo
Author-email: sppedflyer@gmail.com
License: UNKNOWN
Platform: UNKNOWN
